<?xml version="1.0" encoding="utf-8" ?>
<dwsync>
<file name="estilos.css" server="G:/xampp/htdocs/Marajo/" local="129179332761533203" remote="129179332760000000" />
<file name="fontes.css" server="G:/xampp/htdocs/Marajo/" local="129179232933417968" remote="129179232930000000" />
<file name="topo.php" server="G:/xampp/htdocs/Marajo/" local="129240408012470703" remote="129240408010000000" />
<file name="coluna-lateral.php" server="G:/xampp/htdocs/Marajo/" local="129179365952119140" remote="129179365950000000" />
<file name="coluna-meio.php" server="G:/xampp/htdocs/Marajo/" local="129179345266611328" remote="129179345260000000" />
<file name="rodape.php" server="G:/xampp/htdocs/Marajo/" local="129179193627968750" remote="129179193620000000" />
<file name="index.php" server="G:/xampp/htdocs/Marajo/" local="129240404569228515" remote="129240404560000000" />
<file name="formNewsletter.js" server="J:/xampp/htdocs/Marajo/" local="129242207621269531" remote="129242207620000000" />
<file name="enquete.php" server="J:/xampp/htdocs/Marajo/" local="129253350377958984" remote="129253350370000000" />
<file name="newsletter.php" server="J:/xampp/htdocs/Marajo/" local="129272281410498046" remote="129272281410000000" />
<file name="estilos.css" server="J:/xampp/htdocs/Marajo/" local="129274095830332031" remote="129274095830000000" />
<file name="enquente.css" server="J:/xampp/htdocs/Marajo/" local="129253336344306640" remote="129253336340000000" />
<file name="fontes.css" server="J:/xampp/htdocs/Marajo/" local="129179232933417968" remote="129179232930000000" />
<file name="newsletter.css" server="J:/xampp/htdocs/Marajo/" local="129241334519355468" remote="129241334510000000" />
<file name="topo.php" server="J:/xampp/htdocs/Marajo/" local="129272273189316406" remote="129272273180000000" />
<file name="coluna-lateral.php" server="J:/xampp/htdocs/Marajo/" local="129255878911660156" remote="129255878910000000" />
<file name="coluna-meio-marajo.php" server="J:/xampp/htdocs/Marajo/" local="129313021695802608" remote="129313021690000000" />
<file name="rodape.php" server="J:/xampp/htdocs/Marajo/" local="129240458207880859" remote="129240458200000000" />
<file name="marajo.php" server="J:/xampp/htdocs/Marajo/" local="129254194233876953" remote="129254194230000000" />
</dwsync>